.travis.yml
NOTICE.txt
README.rst
bootstrap.py
buildout.cfg
edrnsite.collaborations.sublime-project
setup.cfg
setup.py
travis.cfg
docs/HISTORY.txt
docs/INSTALL.txt
docs/LICENSE.txt
edrnsite/__init__.py
edrnsite.collaborations.egg-info/PKG-INFO
edrnsite.collaborations.egg-info/SOURCES.txt
edrnsite.collaborations.egg-info/dependency_links.txt
edrnsite.collaborations.egg-info/entry_points.txt
edrnsite.collaborations.egg-info/namespace_packages.txt
edrnsite.collaborations.egg-info/not-zip-safe
edrnsite.collaborations.egg-info/requires.txt
edrnsite.collaborations.egg-info/top_level.txt
edrnsite/collaborations/README.rst
edrnsite/collaborations/__init__.py
edrnsite/collaborations/config.py
edrnsite/collaborations/configure.zcml
edrnsite/collaborations/overrides.zcml
edrnsite/collaborations/testing.py
edrnsite/collaborations/upgrades.py
edrnsite/collaborations/upgrades.zcml
edrnsite/collaborations/actions/__init__.py
edrnsite/collaborations/actions/configure.zcml
edrnsite/collaborations/actions/mail.py
edrnsite/collaborations/browser/__init__.py
edrnsite/collaborations/browser/collaborationsfolder.py
edrnsite/collaborations/browser/collaborativegroup.py
edrnsite/collaborations/browser/collaborativegroupindex.py
edrnsite/collaborations/browser/configure.zcml
edrnsite/collaborations/browser/groupevent.py
edrnsite/collaborations/browser/groupspace.py
edrnsite/collaborations/browser/groupspaceindex.py
edrnsite/collaborations/browser/images/blue-book.png
edrnsite/collaborations/browser/images/collaborationsfolder.gif
edrnsite/collaborations/browser/images/collaborativegroup.gif
edrnsite/collaborations/browser/images/collaborativegroupindex.gif
edrnsite/collaborations/browser/images/flask.png
edrnsite/collaborations/browser/images/green-book.png
edrnsite/collaborations/browser/images/groupevent.gif
edrnsite/collaborations/browser/images/groupspace.png
edrnsite/collaborations/browser/images/groupspaceindex.png
edrnsite/collaborations/browser/images/highlight.gif
edrnsite/collaborations/browser/images/highlights.png
edrnsite/collaborations/browser/images/horn.png
edrnsite/collaborations/browser/images/isometric-people.png
edrnsite/collaborations/browser/images/projects.png
edrnsite/collaborations/browser/images/silhouette.png
edrnsite/collaborations/browser/stylesheets/main.css
edrnsite/collaborations/browser/templates/collaboration_summary_report.pt
